nowcasting_utils/__init__.py
nowcasting_utils/version.py
nowcasting_utils/metrics/__init__.py
nowcasting_utils/metrics/evaluation.py
nowcasting_utils/metrics/plot.py
nowcasting_utils/metrics/utils.py
nowcasting_utils/metrics/validation.py
nowcasting_utils/models/__init__.py
nowcasting_utils/models/base.py
nowcasting_utils/models/hub.py
nowcasting_utils/models/loss.py
nowcasting_utils/models/metrics.py
nowcasting_utils/models/normalization.py
nowcasting_utils/models/losses/FocalLoss.py
nowcasting_utils/models/losses/StructuralSimilarity.py
nowcasting_utils/models/losses/TotalVariationLoss.py
nowcasting_utils/models/losses/__init__.py
nowcasting_utils/training/__init__.py
nowcasting_utils/training/callbacks.py
nowcasting_utils/visualization/__init__.py
nowcasting_utils/visualization/line.py
nowcasting_utils/visualization/utils.py
nowcasting_utils/visualization/visualization.py
nowcasting_utils-0.0.42.dist-info/LICENSE
nowcasting_utils-0.0.42.dist-info/METADATA
nowcasting_utils-0.0.42.dist-info/WHEEL
nowcasting_utils-0.0.42.dist-info/top_level.txt
nowcasting_utils-0.0.42.dist-info/RECORD
