Metadata-Version: 2.1
Name: nowcasting-utils
Version: 0.0.42
Summary: Nowcasting Utilities
Home-page: https://github.com/openclimatefix/nowcasting_utils
Author: Jacob Bieker, Jack Kelly, Peter Dudfield
Author-email: jacob@openclimatefix.org
License: MIT
Keywords: artificial intelligence,deep learning,transformer
Classifier: Development Status :: 4 - Beta
Classifier: Intended Audience :: Developers
Classifier: Topic :: Scientific/Engineering :: Artificial Intelligence
Classifier: License :: OSI Approved :: MIT License
Classifier: Programming Language :: Python :: 3.6
License-File: LICENSE
Requires-Dist: huggingface-hub (>=0.0.16)
Requires-Dist: einops (>=0.3.2)
Requires-Dist: pytest
Requires-Dist: numpy
Requires-Dist: tilemapbase
Requires-Dist: plotly
Requires-Dist: nowcasting-dataset
Requires-Dist: nowcasting-dataloader
Requires-Dist: pytorch-msssim
Requires-Dist: torchvision
Requires-Dist: pytorch-lightning
Requires-Dist: neptune-client
